{
    "resource_pack_name": "ToyphoneRP",
    "texture_name": "atlas.items",
    "texture_data": {
        "toyphone": {
            "textures": "textures/items/toyphone_item"
        },"toyphone_blue": {
            "textures": "textures/items/toyphone_item_blue"
        },"toyphone_red": {
            "textures": "textures/items/toyphone_item_red"
        },"toyphone_white": {
            "textures": "textures/items/toyphone_item_white"
        },"kaihuku_kit1": {
            "textures": "textures/items/kaihuku_kit_item1"
        },"kaihuku_kit2": {
            "textures": "textures/items/kaihuku_kit_item2"
        },"kaihuku_kit3": {
            "textures": "textures/items/kaihuku_kit_item3"
        },"fabric": {
            "textures": "textures/items/fabric"
        }
    }
}